Metadata-Version: 2.1
Name: camp-parser
Version: 0.3
Summary: unofficial api to get information from camphub and other camp/competition news website. in thai
Home-page: https://github.com/HRNPH/Camphub_api_unofficial
Author: HRNPH
Author-email: hirunkul2548@gmail.com
License: MIT
Keywords: camp_parser
Platform: UNKNOWN
License-File: LICENSE.md
